sse_plugin_interface/__init__.py
sse_plugin_interface/datatypes.py
sse_plugin_interface/flags.py
sse_plugin_interface/group.py
sse_plugin_interface/plugin.py
sse_plugin_interface/plugin_string.py
sse_plugin_interface/py.typed
sse_plugin_interface/record.py
sse_plugin_interface/string_records.py
sse_plugin_interface/subrecord.py
sse_plugin_interface/utilities.py
sse_plugin_interface-1.0.1.dist-info/licenses/LICENSE
sse_plugin_interface-1.0.1.dist-info/METADATA
sse_plugin_interface-1.0.1.dist-info/WHEEL
sse_plugin_interface-1.0.1.dist-info/top_level.txt
sse_plugin_interface-1.0.1.dist-info/RECORD
