Metadata-Version: 2.4
Name: sse-plugin-interface
Version: 1.0.1
Summary: A pure Python library for reading and writing Skyrim Special Edition Plugin files (.esp, .esm, .esl).
Author-email: Cutleast <cutleast@gmail.com>
License: MIT License
Project-URL: Homepage, https://github.com/cutleast/sse-plugin-interface
Project-URL: Issues, https://github.com/cutleast/sse-plugin-interface/issues
Classifier: Programming Language :: Python :: 3
Classifier: Operating System :: OS Independent
Requires-Python: >=3.12
License-File: LICENSE
Dynamic: license-file
